aesthetic_ascii2/RobotoMono-VariableFont_wght.ttf
aesthetic_ascii2/__init__.py
aesthetic_ascii2/city_test.png
aesthetic_ascii2/synthesize.py
aesthetic_ascii2-0.0.1.dist-info/LICENSE
aesthetic_ascii2-0.0.1.dist-info/METADATA
aesthetic_ascii2-0.0.1.dist-info/WHEEL
aesthetic_ascii2-0.0.1.dist-info/top_level.txt
aesthetic_ascii2-0.0.1.dist-info/RECORD
